processing/__init__.py
processing/combination.py
processing/transformation.py
utils/__init__.py
utils/io.py
utils/plot.py
Comparador_de_imagenes-0.0.1.dist-info/METADATA
Comparador_de_imagenes-0.0.1.dist-info/WHEEL
Comparador_de_imagenes-0.0.1.dist-info/top_level.txt
Comparador_de_imagenes-0.0.1.dist-info/RECORD
