Metadata-Version: 2.1
Name: Comparador-de-imagenes
Version: 0.0.1
Summary: Comparacion de imagenes.
Home-page: https://github.com/Estebanjgg/image_processing
Author: Esteban Gonzalez
Author-email: esteban030990@gmail.com
Requires-Python: >=3.8
Requires-Dist: matplotlib
Requires-Dist: numpy
Requires-Dist: scikit-image (>=0.16.1)
